py_micro_hil/__init__.py
py_micro_hil/assertions.py
py_micro_hil/cli.py
py_micro_hil/framework_API.py
py_micro_hil/logger.py
py_micro_hil/peripheral_config_loader.py
py_micro_hil/peripheral_manager.py
py_micro_hil/report_generator.py
py_micro_hil/tests_framework.py
py_micro_hil/tests_group_factory.py
py_micro_hil/peripherals/RPiPeripherals.py
py_micro_hil/peripherals/__init__.py
py_micro_hil/peripherals/dummyRPiPeripherals.py
py_micro_hil/peripherals/peripherals.py
py_micro_hil/peripherals/protocols.py
py_micro_hil/templates/dark_style.css
py_micro_hil/templates/light_style.css
py_micro_hil/templates/report_template.html
py_micro_hil/templates/styles.css
py_micro_hil/templates/test_code_template.html
py_micro_hil/templates/test_group_template.py
py_micro_hil/utils/__init__.py
py_micro_hil/utils/system.py
py_micro_hil-0.1.6.dist-info/licenses/LICENSE
py_micro_hil-0.1.6.dist-info/METADATA
py_micro_hil-0.1.6.dist-info/WHEEL
py_micro_hil-0.1.6.dist-info/entry_points.txt
py_micro_hil-0.1.6.dist-info/top_level.txt
py_micro_hil-0.1.6.dist-info/RECORD
