Metadata-Version: 2.4
Name: py-micro-hil
Version: 0.1.6
Summary: Hardware-in-the-Loop testing framework
Author-email: niwciu <niwciu@gmail.com>
License: Copyright (c) 2025, niwciu
Project-URL: Homepage, https://github.com/sandra/py-micro-hil
Project-URL: Repository, https://github.com/sandra/py-micro-hil
Project-URL: Issues, https://github.com/sandra/py-micro-hil/issues
Requires-Python: >=3.8
License-File: LICENSE
Requires-Dist: pyserial>=3.5
Requires-Dist: PyYAML>=6.0.2
Requires-Dist: RPi.GPIO>=0.7
Requires-Dist: spidev>=3.6
Requires-Dist: pymodbus>=3.11.4
Requires-Dist: smbus2>=0.4
Requires-Dist: jinja2>=3.1
Requires-Dist: termcolor>=3.2
Provides-Extra: dev
Requires-Dist: pytest>=7.0; extra == "dev"
Requires-Dist: pytest-cov>=4.0; extra == "dev"
Requires-Dist: flake8>=6.0; extra == "dev"
Requires-Dist: black>=23.0; extra == "dev"
Requires-Dist: build>=1.0; extra == "dev"
Requires-Dist: twine>=4.0; extra == "dev"
Dynamic: license-file
